textminer/__init__.py
textminer/cleaner.py
textminer/detector.py
textminer/keyword.py
textminer/summarizer.py
textminerpro-0.0.1.dist-info/METADATA
textminerpro-0.0.1.dist-info/WHEEL
textminerpro-0.0.1.dist-info/top_level.txt
textminerpro-0.0.1.dist-info/RECORD
